odoo/addons/shopinvader_portal_mode/README.rst
odoo/addons/shopinvader_portal_mode/__init__.py
odoo/addons/shopinvader_portal_mode/__manifest__.py
odoo/addons/shopinvader_portal_mode/i18n/shopinvader_portal_mode.pot
odoo/addons/shopinvader_portal_mode/models/__init__.py
odoo/addons/shopinvader_portal_mode/models/shopinvader_backend.py
odoo/addons/shopinvader_portal_mode/readme/CONTRIBUTORS.rst
odoo/addons/shopinvader_portal_mode/readme/CREDITS.rst
odoo/addons/shopinvader_portal_mode/readme/DESCRIPTION.rst
odoo/addons/shopinvader_portal_mode/services/__init__.py
odoo/addons/shopinvader_portal_mode/services/sale.py
odoo/addons/shopinvader_portal_mode/static/description/index.html
odoo/addons/shopinvader_portal_mode/tests/__init__.py
odoo/addons/shopinvader_portal_mode/tests/common.py
odoo/addons/shopinvader_portal_mode/tests/test_invoice.py
odoo/addons/shopinvader_portal_mode/tests/test_sale.py
odoo/addons/shopinvader_portal_mode/views/shopinvader_backend.xml
odoo13_addon_shopinvader_portal_mode-13.0.1.1.1.dist-info/METADATA
odoo13_addon_shopinvader_portal_mode-13.0.1.1.1.dist-info/WHEEL
odoo13_addon_shopinvader_portal_mode-13.0.1.1.1.dist-info/top_level.txt
odoo13_addon_shopinvader_portal_mode-13.0.1.1.1.dist-info/RECORD
